starbie/__init__.py
starbie-0.0.0.dist-info/METADATA
starbie-0.0.0.dist-info/WHEEL
starbie-0.0.0.dist-info/top_level.txt
starbie-0.0.0.dist-info/RECORD
