Metadata-Version: 2.1
Name: starbie
Version: 0.0.0
Summary: statarb
Author: Robert Stanton
Author-email: robertmstanton@proton.me
Keywords: finance,python,quant,statistical arbitrage,mean reversion
Classifier: Development Status :: 4 - Beta
Classifier: Programming Language :: Python :: 3
Classifier: Intended Audience :: Science/Research
Classifier: License :: OSI Approved :: GNU General Public License v3 (GPLv3)
Classifier: Operating System :: OS Independent
Requires-Python: >=3.10
